wie_oshook/.gitignore
wie_oshook/__init__.py
wie_oshook/setup.cfg
wie_oshook/wie_oshook.py
wie_oshook-1.1.dist-info/LICENSE.txt
wie_oshook-1.1.dist-info/METADATA
wie_oshook-1.1.dist-info/WHEEL
wie_oshook-1.1.dist-info/RECORD
